konnichiha/__init__.py
konnichiha/main.py
tests/__init__.py
tests/test_main.py
konnichiha-0.1.1.dist-info/METADATA
konnichiha-0.1.1.dist-info/WHEEL
konnichiha-0.1.1.dist-info/top_level.txt
konnichiha-0.1.1.dist-info/RECORD
