Metadata-Version: 2.2
Name: konnichiha
Version: 0.1.1
Summary: A Python project named konnichiha
Requires-Python: >=3.9.0
Requires-Dist: build
Requires-Dist: twine
Requires-Dist: maturin
Provides-Extra: dev
Requires-Dist: ruff; extra == "dev"
Requires-Dist: pytest; extra == "dev"
